hctestbyqy/__init__.py
hctestbyqy/file_upload.py
hctestbyqy/image_recognition.py
hctestbyqy/report_screenshot.py
hctestbyqy-1.0.0.dist-info/METADATA
hctestbyqy-1.0.0.dist-info/WHEEL
hctestbyqy-1.0.0.dist-info/top_level.txt
hctestbyqy-1.0.0.dist-info/RECORD
