Metadata-Version: 2.1
Name: hctestbyqy
Version: 1.0.0
Requires-Dist: selenium
Requires-Dist: pyautogui
Requires-Dist: opencv-python
Requires-Dist: pytesseract
Requires-Dist: allure-pytest
